LICENSE
README.md
setup.py
mintf/__init__.py
mintf/frame.py
mintf/graph.py
mintf/plt.py
mintf.egg-info/PKG-INFO
mintf.egg-info/SOURCES.txt
mintf.egg-info/dependency_links.txt
mintf.egg-info/requires.txt
mintf.egg-info/top_level.txt
tests/test_frame.py
tests/test_graph.py