Metadata-Version: 2.4
Name: mintf
Version: 0.1.0
Summary: Minimalist Python spatial transformation utils.
Home-page: https://github.com/yanghn2002/mintf
Author: yanghn2002
Requires-Python: >=3.10
License-File: LICENSE
Requires-Dist: numpy
Requires-Dist: numpy-quaternion
Provides-Extra: plt
Requires-Dist: matplotlib; extra == "plt"
Provides-Extra: test
Requires-Dist: pytest; extra == "test"
Requires-Dist: scipy; extra == "test"
Dynamic: author
Dynamic: home-page
Dynamic: license-file
Dynamic: provides-extra
Dynamic: requires-dist
Dynamic: requires-python
Dynamic: summary
